bowie/make_plot.py
bowie/makeplot_dict_info.txt
bowie/plotutils/__init__.py
bowie/plotutils/baseplot.py
bowie/plotutils/forminput.py
bowie/plotutils/makeprocess.py
bowie/plotutils/plottypes.py
bowie/plotutils/readdata.py
bowie-2.0.1.dist-info/LICENSE
bowie-2.0.1.dist-info/METADATA
bowie-2.0.1.dist-info/WHEEL
bowie-2.0.1.dist-info/top_level.txt
bowie-2.0.1.dist-info/RECORD
