Metadata-Version: 2.1
Name: bowie
Version: 2.0.1
Summary: Binary Observability with Illustrative Exploration (BOWIE)
Home-page: https://github.com/mikekatz04/BOWIE
Author: Michael Katz
Author-email: mikekatz04@gmail.com
License: UNKNOWN
Platform: UNKNOWN
Classifier: Programming Language :: Python :: 3
Classifier: Operating System :: OS Independent
Requires-Dist: gwsnrcalc
Requires-Dist: numpy
Requires-Dist: scipy
Requires-Dist: astropy
Requires-Dist: h5py
Requires-Dist: matplotlib
